setup.py
ServerTime/CLI.py
ServerTime/ServerTime.py
ServerTime/__init__.py
ServerTime.egg-info/PKG-INFO
ServerTime.egg-info/SOURCES.txt
ServerTime.egg-info/dependency_links.txt
ServerTime.egg-info/top_level.txt